README.rst
setup.cfg
setup.py
fsa4streams/__init__.py
fsa4streams/fsa.py
fsa4streams/matcher.py
fsa4streams/state.py
fsa4streams.egg-info/PKG-INFO
fsa4streams.egg-info/SOURCES.txt
fsa4streams.egg-info/dependency_links.txt
fsa4streams.egg-info/top_level.txt