Metadata-Version: 1.0
Name: fsa4streams
Version: 0.8
Summary: An implementation of Finite State Automata for event streams
Home-page: UNKNOWN
Author: Pierre-Antoine Champin
Author-email: UNKNOWN
License: LGPL v3
Platform: OS Independant
